MANIFEST.in
README.txt
setup.py
sequenza/__init__.py
sequenza/__version__.py
sequenza/bgzf.py
sequenza/commands.py
sequenza/fasta.py
sequenza/izip.py
sequenza/misc.py
sequenza/pileup.py
sequenza/samtools.py
sequenza/seqz.py
sequenza/varscan.py
sequenza/vcf.py
sequenza/wig.py
sequenza/programs/__init__.py
sequenza/programs/bam2seqz.py
sequenza/programs/gc_wiggle.py
sequenza/programs/pileup2acgt.py
sequenza/programs/seqz_binning.py
sequenza/programs/seqz_merge.py
sequenza/programs/snp2seqz.py
sequenza/src/common.h
sequenza/src/parsers.c
sequenza/src/parsers.h
sequenza/src/pileup.c
sequenza_utils.egg-info/PKG-INFO
sequenza_utils.egg-info/SOURCES.txt
sequenza_utils.egg-info/dependency_links.txt
sequenza_utils.egg-info/entry_points.txt
sequenza_utils.egg-info/top_level.txt
test/test_commands.py
test/test_fasta.py
test/test_izip.py
test/test_misc.py
test/test_pileup.py
test/test_seqz.py
test/test_wig.py